cz_jira_ticket_prefix.py
CommitizenJiraTicketPrefix-0.1.1.dist-info/LICENSE
CommitizenJiraTicketPrefix-0.1.1.dist-info/METADATA
CommitizenJiraTicketPrefix-0.1.1.dist-info/WHEEL
CommitizenJiraTicketPrefix-0.1.1.dist-info/entry_points.txt
CommitizenJiraTicketPrefix-0.1.1.dist-info/top_level.txt
CommitizenJiraTicketPrefix-0.1.1.dist-info/RECORD
