Metadata-Version: 2.1
Name: CommitizenJiraTicketPrefix
Version: 0.1.1
License-File: LICENSE
Requires-Dist: commitizen
